ontoma/__init__.py
ontoma/nlp_pipeline.py
ontoma/ontoma.py
ontoma/common/__init__.py
ontoma/common/schemas.py
ontoma/common/utils.py
ontoma/dataset/__init__.py
ontoma/dataset/dataset.py
ontoma/dataset/normalised_entity_lut.py
ontoma/dataset/raw_entity_lut.py
ontoma/dataset/ready_entity_lut.py
ontoma/datasource/__init__.py
ontoma/datasource/disease.py
ontoma/datasource/disease_curation.py
ontoma/datasource/drug.py
ontoma/datasource/target.py
ontoma/schemas/__init__.py
ontoma/schemas/normalised_entity_lut.json
ontoma/schemas/raw_entity_lut.json
ontoma/schemas/ready_entity_lut.json
ontoma-2.1.1.dist-info/METADATA
ontoma-2.1.1.dist-info/WHEEL
ontoma-2.1.1.dist-info/licenses/LICENSE
ontoma-2.1.1.dist-info/RECORD
