Metadata-Version: 2.4
Name: ontoma
Version: 2.1.1
Summary: Ontology mapping for Open Targets
License-File: LICENSE
Requires-Python: >=3.10
Requires-Dist: ipykernel>=6.30.1
Requires-Dist: numpy>=2.2.6
Requires-Dist: pyspark==3.5.7
Requires-Dist: spark-nlp==6.1.5
